{
  "sid": "GR139",
  "idx": 1,
  "sh": 103,
  "t": "Gamma",
  "rh": 133,
  "ll": {
    "lat": 39.231083,
    "long": -44.341866
  },
  "pa": "p1,p10,p12,p14,p15,p17,p18,p19,p2,p27,p28,p29,p3,p33,p35,p36,p37,p39,p40,t1,t4,t5,t8",
  "pp": "p11,p13,p16,p20,p21,p22,p23,p24,p25,p26,p30,p31,p32,p34,p38,p4,p41,p42,p43,p5,p6,p7,p8,p9,t2,t3,t6,t7,t9",
  "og": "ACEFGHIKLOP",
  "ao": [
    "A07-ur,ca-B15-",
    "A19-ur,ur-B14-",
    "C08-to,or-C19-",
    "C10-to,to-C15-",
    "E07-ca,to-H17-",
    "F02-or,ur-T17-",
    "F08-or,ca-T16-",
    "G03-or,re-T20-",
    "H03-ta,ta-L16-",
    "H06-ta,or-L19-",
    "H08-ta,ur-L18-",
    "H36-ta,ca-L17-",
    "H56-ta-L15-",
    "I05-ur,re-B19-",
    "I14-ur,re-B19-",
    "K07-or,ca-T16-",
    "K08-or,or-T15-",
    "L08-or,ta-T18-",
    "L10-or,re-T20-",
    "O07-ca,ca-H18-",
    "P07-to,ca-C16-"
  ],
  "rth": "t2:133,t3:131,t6:145,t7:133,t9:133"
}